digikala_bi_test/__init__.py
digikala_bi_test-0.2.0.dist-info/METADATA
digikala_bi_test-0.2.0.dist-info/WHEEL
digikala_bi_test-0.2.0.dist-info/RECORD
