Metadata-Version: 2.1
Name: digikala-bi-test
Version: 0.2.0
Summary: 
Author: meysam
Author-email: meysamaghili533@gmail.com
Requires-Python: >=3.11,<4.0
Classifier: Programming Language :: Python :: 3
Classifier: Programming Language :: Python :: 3.11
Classifier: Programming Language :: Python :: 3.12
Requires-Dist: pandas (>=2.1.4,<3.0.0)
